mygui/__init__.py
mygui/Examples/LgridExamples.py
mygui/Examples/MYGUI-egrid.py
mygui/Examples/MYGUI-lgrid.py
mygui/Examples/testmygui.py
mygui/test/lgridegridtest.py
mygui/test/testmygui.py
mygui-0.3.1.dist-info/LICENSE.md
mygui-0.3.1.dist-info/METADATA
mygui-0.3.1.dist-info/WHEEL
mygui-0.3.1.dist-info/top_level.txt
mygui-0.3.1.dist-info/RECORD
