Metadata-Version: 2.1
Name: mygui
Version: 0.3.1
Summary: A Simple icon to replace the tkinter feather for your programs
Home-page: https://github.com/Caveman-Software/mygui
Author: Michael E Mulvey
Author-email: "michael.e.mulvey@gmail.com"
Project-URL: Bug Tracker, https://github.com/Caveman-Software/mygui/issues
Classifier: Programming Language :: Python :: 3 :: Only
Classifier: Programming Language :: Python :: 3.12
Classifier: License :: OSI Approved :: MIT License
Classifier: Operating System :: OS Independent
Classifier: Operating System :: Microsoft :: Windows :: Windows 10
Requires-Python: >=3.11
License-File: LICENSE.md
